lyric/__init__.py
lyric/test.py
python_lyric-1.1.6.dist-info/LICENSE.md
python_lyric-1.1.6.dist-info/METADATA
python_lyric-1.1.6.dist-info/WHEEL
python_lyric-1.1.6.dist-info/top_level.txt
python_lyric-1.1.6.dist-info/RECORD
